{"assets/images/.DS_Store":["assets/images/.DS_Store"],"assets/images/hand-left.svg":["assets/images/hand-left.svg"],"assets/images/hand-right.svg":["assets/images/hand-right.svg"],"assets/images/logo2.jpg":["assets/images/logo2.jpg"],"assets/images/r_item_0.png":["assets/images/r_item_0.png"],"assets/images/r_item_1.png":["assets/images/r_item_1.png"],"assets/images/r_item_2.png":["assets/images/r_item_2.png"],"assets/images/r_item_3.png":["assets/images/r_item_3.png"],"assets/images/r_item_4.png":["assets/images/r_item_4.png"],"assets/images/r_item_5.png":["assets/images/r_item_5.png"],"assets/images/r_item_6.png":["assets/images/r_item_6.png"],"assets/images/r_item_7.png":["assets/images/r_item_7.png"],"assets/images/r_item_8.png":["assets/images/r_item_8.png"],"assets/images/r_item_9.png":["assets/images/r_item_9.png"],"assets/images/slot_bg.png":["assets/images/slot_bg.png"],"assets/images/slot_bg2.png":["assets/images/slot_bg2.png"],"assets/images/slot_bg_bg.png":["assets/images/slot_bg_bg.png"],"assets/images/slot_bg_bg2.png":["assets/images/slot_bg_bg2.png"],"assets/images/table.png":["assets/images/table.png"],"assets/sounds/.DS_Store":["assets/sounds/.DS_Store"],"assets/sounds/pull-slot.mp3":["assets/sounds/pull-slot.mp3"],"assets/sounds/spin-loop.mp3":["assets/sounds/spin-loop.mp3"],"assets/sounds/stop.mp3":["assets/sounds/stop.mp3"],"assets/sounds/win-end.mp3":["assets/sounds/win-end.mp3"],"assets/sounds/win-loop.mp3":["assets/sounds/win-loop.mp3"],"packages/cupertino_icons/assets/CupertinoIcons.ttf":["packages/cupertino_icons/assets/CupertinoIcons.ttf"]}